sikriml_core/__init__.py
sikriml_core/config.py
sikriml_core/environment/__init__.py
sikriml_core/environment/aml_environment.py
sikriml_core/environment/configs/__init__.py
sikriml_core/environment/configs/environment_config.py
sikriml_core/environment/errors/__init__.py
sikriml_core/environment/errors/aml_build_image_error.py
sikriml_core/experiment/__init__.py
sikriml_core/experiment/experiment_abs.py
sikriml_core/experiment/pipeline/__init__.py
sikriml_core/experiment/pipeline/pipeline_experiment.py
sikriml_core/experiment/script/__init__.py
sikriml_core/experiment/script/script_experiment.py
sikriml_core/helpers/__init__.py
sikriml_core/helpers/io/__init__.py
sikriml_core/helpers/io/json_file_helper.py
sikriml_core/helpers/io/txt_file_helper.py
sikriml_core/helpers/io/yaml_file_helper.py
sikriml_core/helpers/io/abstracts/__init__.py
sikriml_core/helpers/io/abstracts/serializable_interface.py
sikriml_core/models/__init__.py
sikriml_core/models/ner/__init__.py
sikriml_core/models/ner/processor_base.py
sikriml_core/models/ner/score_entity.py
sikriml_core/models/ner/score_label.py
sikriml_core/models/ner/tokenizer/__init__.py
sikriml_core/models/ner/tokenizer/token_data.py
sikriml_core/models/ner/tokenizer/tokenizer.py
sikriml_core/models/ner/tokenizer/abstracts/__init__.py
sikriml_core/models/ner/tokenizer/abstracts/tokenizer_base.py
sikriml_core/webservice/__init__.py
sikriml_core/webservice/web_service_abs.py
sikriml_core/webservice/web_service_config.py
sikriml_core/webservice/aci/__init__.py
sikriml_core/webservice/aci/aci_web_service.py
sikriml_core/webservice/aks/__init__.py
sikriml_core/webservice/aks/aks_web_service.py
sikriml_core/webservice/aks/aks_web_service_config.py
sikriml_core/webservice/configs/__init__.py
sikriml_core/webservice/configs/aci_config.py
sikriml_core/webservice/configs/aks_config.py
sikriml_core/webservice/configs/deploy_config.py
sikriml_core/webservice/local/__init__.py
sikriml_core/webservice/local/local_web_service.py
sikriml_core-0.1.1b1.dist-info/METADATA
sikriml_core-0.1.1b1.dist-info/WHEEL
sikriml_core-0.1.1b1.dist-info/top_level.txt
sikriml_core-0.1.1b1.dist-info/RECORD
